store_beat/__init__.py
store_beat/api.py
store_beat/app.py
store_beat/scheduler.py
store_beat/store.py
store_beat/worker.py
store_beat/dist/index.html
store_beat/dist/static/css/app.0e5b3341378ca92cb78ea83c505880e6.css
store_beat/dist/static/css/app.0e5b3341378ca92cb78ea83c505880e6.css.map
store_beat/dist/static/js/0.5e83d120bede325a7980.js
store_beat/dist/static/js/0.5e83d120bede325a7980.js.map
store_beat/dist/static/js/1.df0d5ee1f3c23595a8db.js
store_beat/dist/static/js/1.df0d5ee1f3c23595a8db.js.map
store_beat/dist/static/js/app.98726809653c88987ed8.js
store_beat/dist/static/js/app.98726809653c88987ed8.js.map
store_beat/dist/static/js/manifest.39659e10df3ff4e430c1.js
store_beat/dist/static/js/manifest.39659e10df3ff4e430c1.js.map
store_beat/dist/static/js/vendor.c8f8ae451c5bb35e9deb.js
store_beat/dist/static/js/vendor.c8f8ae451c5bb35e9deb.js.map
store_beat-2018.7.2.dist-info/METADATA
store_beat-2018.7.2.dist-info/RECORD
store_beat-2018.7.2.dist-info/WHEEL
store_beat-2018.7.2.dist-info/top_level.txt
