Metadata-Version: 2.1
Name: store-beat
Version: 2018.7.2
Summary: beat with store
Home-page: https://github.com/pingf/store_beat.git
Author: Jesse MENG
Author-email: pingf0@gmail.com
License: BSD
Platform: any
Classifier: Intended Audience :: Developers
Classifier: License :: OSI Approved :: BSD License
Classifier: Operating System :: OS Independent
Classifier: Programming Language :: Python
Classifier: Topic :: Software Development :: Libraries :: Python Modules
Requires-Dist: aiohttp
Requires-Dist: wrap
Requires-Dist: store
Requires-Dist: celery
Requires-Dist: redis
